mdfusion/__init__.py
mdfusion/mdfusion.py
mdfusion/htmlark/htmlark.py
mdfusion/htmlark/setup.py
mdfusion/htmlark/tests/__init__.py
mdfusion/htmlark/tests/test_htmlark.py
mdfusion/reveal/footer.html
mdfusion/reveal/header.html
mdfusion/reveal/public/README.md
mdfusion/reveal/public/headerFooterPlugin.js
mdfusion/reveal/public/slideNumberPlugin.js
mdfusion-0.2.7.dist-info/licenses/LICENSE
mdfusion-0.2.7.dist-info/METADATA
mdfusion-0.2.7.dist-info/WHEEL
mdfusion-0.2.7.dist-info/entry_points.txt
mdfusion-0.2.7.dist-info/top_level.txt
mdfusion-0.2.7.dist-info/RECORD
