Metadata-Version: 2.4
Name: mdfusion
Version: 0.2.7
Summary: Merge Markdown files into a single PDF or HTML presentation with Pandoc + XeLaTeX
Author: ejuet
Requires-Python: >=3.8
License-File: LICENSE
Requires-Dist: toml
Requires-Dist: tdqm
Requires-Dist: simple-parsing
Requires-Dist: beautifulsoup4
Requires-Dist: requests
Dynamic: license-file
